<annotation>
	<folder>VOC2007</folder>
	<filename>009984.jpg</filename>
	<source>
		<database>The VOC2007 Database</database>
		<annotation>PASCAL VOC2007</annotation>
		<image>flickr</image>
		<flickrid>194179466</flickrid>
	</source>
	<owner>
		<flickrid>monsieurrompu</flickrid>
		<name>Thom Zemanek</name>
	</owner>
	<size>
		<width>650</width>
		<height>433</height>
		<depth>3</depth>
	</size>
	<segmented>0</segmented>
	<object>
		<name>fish</name>
		<pose>left</pose>
		<truncated>0</truncated>
		<difficult>0</difficult>
		<bndbox>
			<xmin>184</xmin>
			<ymin>143</ymin>
			<xmax>540</xmax>
			<ymax>319</ymax>
		</bndbox>
	</object>
</annotation>


